itd/__init__.py
itd/client.py
itd/request.py
itd_sdk-0.3.0.dist-info/licenses/LICENSE
itd_sdk-0.3.0.dist-info/METADATA
itd_sdk-0.3.0.dist-info/WHEEL
itd_sdk-0.3.0.dist-info/top_level.txt
itd_sdk-0.3.0.dist-info/RECORD
