Metadata-Version: 2.4
Name: itd-sdk
Version: 0.3.0
Summary: ITD client for python
Author-email: firedotguy <nta16022013@gmail.com>
License-Expression: MIT
Requires-Python: >=3.9
License-File: LICENSE
Requires-Dist: requests
Dynamic: license-file
Dynamic: requires-python
